bytecheckpoint/__init__.py
bytecheckpoint/config.py
bytecheckpoint/version.py
bytecheckpoint/__pycache__/__init__.cpython-310.pyc
bytecheckpoint/__pycache__/__init__.cpython-312.pyc
bytecheckpoint/__pycache__/config.cpython-310.pyc
bytecheckpoint/__pycache__/config.cpython-312.pyc
bytecheckpoint/__pycache__/version.cpython-310.pyc
bytecheckpoint/__pycache__/version.cpython-312.pyc
bytecheckpoint/api/__init__.py
bytecheckpoint/api/load.py
bytecheckpoint/api/save.py
bytecheckpoint/api/__pycache__/__init__.cpython-310.pyc
bytecheckpoint/api/__pycache__/__init__.cpython-312.pyc
bytecheckpoint/api/__pycache__/load.cpython-310.pyc
bytecheckpoint/api/__pycache__/load.cpython-312.pyc
bytecheckpoint/api/__pycache__/save.cpython-310.pyc
bytecheckpoint/api/__pycache__/save.cpython-312.pyc
bytecheckpoint/checkpointer/__init__.py
bytecheckpoint/checkpointer/base_checkpointer.py
bytecheckpoint/checkpointer/ddp_checkpointer.py
bytecheckpoint/checkpointer/fsdp2_checkpointer.py
bytecheckpoint/checkpointer/fsdp_checkpointer.py
bytecheckpoint/checkpointer/meta_type.py
bytecheckpoint/checkpointer/__pycache__/__init__.cpython-310.pyc
bytecheckpoint/checkpointer/__pycache__/__init__.cpython-312.pyc
bytecheckpoint/checkpointer/__pycache__/base_checkpointer.cpython-310.pyc
bytecheckpoint/checkpointer/__pycache__/base_checkpointer.cpython-312.pyc
bytecheckpoint/checkpointer/__pycache__/ddp_checkpointer.cpython-310.pyc
bytecheckpoint/checkpointer/__pycache__/ddp_checkpointer.cpython-312.pyc
bytecheckpoint/checkpointer/__pycache__/fsdp2_checkpointer.cpython-310.pyc
bytecheckpoint/checkpointer/__pycache__/fsdp2_checkpointer.cpython-312.pyc
bytecheckpoint/checkpointer/__pycache__/fsdp_checkpointer.cpython-310.pyc
bytecheckpoint/checkpointer/__pycache__/fsdp_checkpointer.cpython-312.pyc
bytecheckpoint/checkpointer/__pycache__/meta_type.cpython-310.pyc
bytecheckpoint/checkpointer/__pycache__/meta_type.cpython-312.pyc
bytecheckpoint/distributed/__init__.py
bytecheckpoint-0.0.2.dist-info/LICENSE
bytecheckpoint-0.0.2.dist-info/METADATA
bytecheckpoint-0.0.2.dist-info/WHEEL
bytecheckpoint-0.0.2.dist-info/top_level.txt
bytecheckpoint-0.0.2.dist-info/RECORD
