Metadata-Version: 2.1
Name: bytecheckpoint
Version: 0.0.2
Summary: ByteCheckpoint: An Unified Checkpointing Library for LFMs
Home-page: https://github.com/ByteDance-Seed/ByteCheckpoint.git
Author: ByteDance-Seed-MLSys
Author-email: wanborui@connect.hku.hk, mingjihan@bytedance.com
License: Apache 2.0
Requires-Python: >=3.8
License-File: LICENSE
Requires-Dist: torch<=2.5.0,>=2.1.0
Requires-Dist: mmh3<=4.2.0,>=4.1.0
Requires-Dist: universal-pathlib<=1.0.0,>=0.2.2
Requires-Dist: cachetools<=10.0.0,>=5.4.0
Requires-Dist: safetensors<=1.0.0,>=0.4.5
Requires-Dist: numpy
Requires-Dist: safetensors
Requires-Dist: typing-extensions
Requires-Dist: grpcio==1.69.0
Requires-Dist: protobuf==3.20.3
